sgespawner/__init__.py
sgespawner/spawner.py
sgespawner/version.py
sgespawner-0.2.4.dist-info/LICENSE.md
sgespawner-0.2.4.dist-info/METADATA
sgespawner-0.2.4.dist-info/WHEEL
sgespawner-0.2.4.dist-info/top_level.txt
sgespawner-0.2.4.dist-info/RECORD
