Metadata-Version: 2.1
Name: sgespawner
Version: 0.2.4
Summary: UNKNOWN
Home-page: https://github.com/willfurnass/sgespawner
Author: Will Furnass
Author-email: w.furnass@sheffield.ac.uk
License: BSD
Platform: UNKNOWN
Classifier: Development Status :: 4 - Beta
Classifier: Intended Audience :: System Administrators
Classifier: License :: OSI Approved :: BSD License
Classifier: Topic :: Utilities
Requires-Dist: markdown
Requires-Dist: jinja2
Requires-Dist: jupyterhub (>=0.7.2)
